clk_divider.v
// clk_divider.v
module clk_divider
#(
    parameter integer DIV = 10 // Must be even
)(
    input  wire clk_in,
    input  wire rst,
    output reg  clk_out
);

    localparam integer TC = (DIV / 2) - 1; // Terminal count
    integer count;

    wire terminate = (count == TC);

    always @(posedge clk_in) begin
        if (rst) begin
            count   <= 0;
            clk_out <= 0;
        end else begin
            if (terminate) begin
                count   <= 0;
                clk_out <= ~clk_out;
            end else begin
                count <= count + 1;
            end
        end
    end

endmodule

clk_divider_tb.v
// clk_divider_tb.v
`timescale 1us / 1ns

module clk_divider_tb;

    // Inputs
    reg clk_in;
    reg rst;

    // Output
    wire clk_out;

    // Instantiate the Device Under Test (DUT)
    clk_divider #( .DIV(10) ) DUT (
        .clk_in  ( clk_in  ), // 1 kHz
        .rst     ( rst     ),
        .clk_out ( clk_out )  // 100 Hz
    );

    // Generate 1 kHz clock: 1 ms period = 500 us high, 500 us low
    initial clk_in = 0;
    always #500 clk_in = ~clk_in;

    // Stimulus block
    initial begin
        // Dump waveform
        $dumpfile("clk_divider.vcd");
        $dumpvars(0, clk_divider_tb);

        // Apply reset
        rst = 1;
        #2000; // Wait 2 ms
        rst = 0;

        // Let simulation run for 60 ms
        #60000;
        $finish;
    end

endmodule

clk_divider.vcd
$date
	Tue Jul 15 14:08:44 2025
$end
$version
	Icarus Verilog
$end
$timescale
	1ns
$end
$scope module clk_divider_tb $end
$var wire 1 ! clk_out $end
$var reg 1 " clk_in $end
$var reg 1 # rst $end
$scope module DUT $end
$var wire 1 " clk_in $end
$var wire 1 # rst $end
$var wire 1 $ terminate $end
$var parameter 32 % DIV $end
$var parameter 32 & TC $end
$var reg 1 ! clk_out $end
$var integer 32 ' count [31:0] $end
$upscope $end
$upscope $end
$enddefinitions $end
$comment Show the parameter values. $end
$dumpall
b100 &
b1010 %
$end
#0
$dumpvars
bx '
x$
1#
0"
x!
$end
#500000
0!
0$
b0 '
1"
#1000000
0"
#1500000
1"
#2000000
0"
0#
#2500000
b1 '
1"
#3000000
0"
#3500000
b10 '
1"
#4000000
0"
#4500000
b11 '
1"
#5000000
0"
#5500000
1$
b100 '
1"
#6000000
0"
#6500000
1!
0$
b0 '
1"
#7000000
0"
#7500000
b1 '
1"
#8000000
0"
#8500000
b10 '
1"
#9000000
0"
#9500000
b11 '
1"
#10000000
0"
#10500000
1$
b100 '
1"
#11000000
0"
#11500000
0!
0$
b0 '
1"
#12000000
0"
#12500000
b1 '
1"
#13000000
0"
#13500000
b10 '
1"
#14000000
0"
#14500000
b11 '
1"
#15000000
0"
#15500000
1$
b100 '
1"
#16000000
0"
#16500000
1!
0$
b0 '
1"
#17000000
0"
#17500000
b1 '
1"
#18000000
0"
#18500000
b10 '
1"
#19000000
0"
#19500000
b11 '
1"
#20000000
0"
#20500000
1$
b100 '
1"
#21000000
0"
#21500000
0!
0$
b0 '
1"
#22000000
0"
#22500000
b1 '
1"
#23000000
0"
#23500000
b10 '
1"
#24000000
0"
#24500000
b11 '
1"
#25000000
0"
#25500000
1$
b100 '
1"
#26000000
0"
#26500000
1!
0$
b0 '
1"
#27000000
0"
#27500000
b1 '
1"
#28000000
0"
#28500000
b10 '
1"
#29000000
0"
#29500000
b11 '
1"
#30000000
0"
#30500000
1$
b100 '
1"
#31000000
0"
#31500000
0!
0$
b0 '
1"
#32000000
0"
#32500000
b1 '
1"
#33000000
0"
#33500000
b10 '
1"
#34000000
0"
#34500000
b11 '
1"
#35000000
0"
#35500000
1$
b100 '
1"
#36000000
0"
#36500000
1!
0$
b0 '
1"
#37000000
0"
#37500000
b1 '
1"
#38000000
0"
#38500000
b10 '
1"
#39000000
0"
#39500000
b11 '
1"
#40000000
0"
#40500000
1$
b100 '
1"
#41000000
0"
#41500000
0!
0$
b0 '
1"
#42000000
0"
#42500000
b1 '
1"
#43000000
0"
#43500000
b10 '
1"
#44000000
0"
#44500000
b11 '
1"
#45000000
0"
#45500000
1$
b100 '
1"
#46000000
0"
#46500000
1!
0$
b0 '
1"
#47000000
0"
#47500000
b1 '
1"
#48000000
0"
#48500000
b10 '
1"
#49000000
0"
#49500000
b11 '
1"
#50000000
0"
#50500000
1$
b100 '
1"
#51000000
0"
#51500000
0!
0$
b0 '
1"
#52000000
0"
#52500000
b1 '
1"
#53000000
0"
#53500000
b10 '
1"
#54000000
0"
#54500000
b11 '
1"
#55000000
0"
#55500000
1$
b100 '
1"
#56000000
0"
#56500000
1!
0$
b0 '
1"
#57000000
0"
#57500000
b1 '
1"
#58000000
0"
#58500000
b10 '
1"
#59000000
0"
#59500000
b11 '
1"
#60000000
0"
#60500000
1$
b100 '
1"
#61000000
0"
#61500000
0!
0$
b0 '
1"
